{"metadata": {"length": 921, "words": 169, "reading_time_min": 0.845}, "text": "Yo andaba entre la sombra,\n\ncuando como un fulgor llegaste t\u00fa; de pronto,\n\ncon el \u00faltimo amor.\n\nPero bast\u00f3 un efluvio de antiguas primaveras\n\npara reconocerte, para saber qui\u00e9n eras.\n\nY eras la misteriosa mujer desconocida\n\nque entristeci\u00f3 de un sue\u00f1o lo mejor de mi vida;\n\nla de las tardes grises y los claros de luna,\n\nla que busqu\u00e9 entre tantas y no encontr\u00e9 en ninguna.\n\nY hoy tal vez como un premio, tal vez como un castigo,\n\nlo mejor de mi vida ser\u00e1 morir contigo.\n\nHe pensado esta noche, sinti\u00e9ndote tan m\u00eda\n\nque as\u00ed como llegaste, pudieras irte un d\u00eda.\n\nLo he pensado eso es todo, pero si sucediera,\n\ndejar\u00e9 que te vayas sin un adi\u00f3s siquiera.\n\nY cuando te hayas ido yo que nunca me quejo,\n\nme vestir\u00e9 de luto y aprender\u00e9 a ser viejo.\n\nPero si me muriera sin poder olvidarte\n\ny despu\u00e9s de la muerte se llega a alguna parte;\n\npreguntar\u00e9 si hay sitio, para m\u00ed, junto a ti.\n\nY Dios, seguramente, responder\u00e1 que s\u00ed.\n\n"}