{"metadata": {"length": 521, "words": 89, "reading_time_min": 0.445}, "text": "Vi\u00e9ndome Fili en brazos de la muerte,\n\nheroicamente se movi\u00f3 a clemencia,\n\ny a su altivo decoro dio licencia\n\npara inclinarse a remediar mi suerte.\n\n\nSinti\u00f3 el sujeto, de poder m\u00e1s fuerte\n\nque el natural, la dulce violencia;\n\nque amor en el crisol de la experiencia\n\nlos accidentes en salud convierte.\n\n\nSi ya no huyeron, Fili, de la gloria\n\nque all\u00ed vieron salir de tu belleza,\n\nque en su presencia es todo luz y vida;\n\n\nat\u00f3nita qued\u00f3 naturaleza,\n\ncontra sus mismas leyes socorrida,\n\ny preci\u00e1ndose amor de la victoria.\n\n"}