{"metadata": {"length": 1399, "words": 240, "reading_time_min": 1.2}, "text": "\u00a1La campi\u00f1a!\n\nSobre el c\u00e9sped del cortijo va la ni\u00f1a\n\ntierna, rubia, fr\u00e1gil, blanca;\n\n\u2014bajo el brazo la mu\u00f1eca\n\nde cart\u00f3n rosada y hueca\u2014\n\nsalta, corre, canta, grita,\n\ny sus f\u00falgidos ojazos copian toda\n\nla pureza de la b\u00f3veda infinita.\n\nVedla: es ritmo\n\ny es donaire;\n\nsus desnudos pies se agitan y parece\n\nque tambi\u00e9n tuviesen alas\n\ncomo el aire.\n\n\nDulcemente el aura toca\n\nel capullo de su boca\n\nque es esencia y es frescura\n\ny es panal, h\u00famedo y tibio,\n\nde miel pura.\n\nVa contenta, retozona,\n\nva de prisa;\n\ny en sus labios aletea\n\ncomo un ave sobre el nido, la sonrisa.\n\n\nPrimavera en los jardines,\n\nbosques, valles y barrancas,\n\necha rosas, rosas, rosas,\n\nrosas blancas.\n\nUna crencha rubia miente\n\nun celaje sobre el campo de su frente;\n\nfrente casta,\n\nperla enorme que en el oro de sus rizos\n\narcang\u00e9licos se engasta;\n\nfrente pura que humedece\n\nel sudor, y que parece,\n\nbajo el soplo sano y fr\u00edo\n\nde los c\u00e9firos, camelia\n\nempapada de roc\u00edo.\n\n\nVa la ni\u00f1a; tal vez sue\u00f1a\n\ncon las hadas, y se cuenta\n\nella misma, el cuentecillo\n\nde la pobre Cenicienta.\n\nY sus gritos melodiosos\n\nen las r\u00e1fagas desl\u00ede,\n\njuguetona, parlanchina,\n\nmientras salta, corre y r\u00ede.\n\nNace el alba; vibra el orto\n\nsus espadas de reflejos,\n\ny el espacio se sonrosa, y un gran vaho\n\nde perfumes acres, llega\n\nde muy lejos.\n\n\nPrimavera en los jardines,\n\nbosques, valles y barrancas,\n\necha rosas, rosas, rosas,\n\nrosas blancas.\n\n"}