{"metadata": {"length": 13658, "words": 2359, "reading_time_min": 11.795}, "text": "Pese a ser considerado un prodigio de belleza, bondad e inteligencia, el peque\u00f1o Giorgio era muy temido en su familia. Todos: sus padres, sus abuelos paternos y las criadas Anna e Ida, viv\u00edan bajo la pesadilla de sus rabietas, pero ninguno de ellos se hubiera atrevido a confesarlo; al contrario, proclamaban con obstinaci\u00f3n que en el mundo no exist\u00eda un ni\u00f1o tan bueno, afectuoso y d\u00f3cil como \u00e9l. Cada cual quer\u00eda sobresalir en esa desenfrenada adoraci\u00f3n, y temblaba ante la idea de poder provocar el llanto del ni\u00f1o de forma involuntaria: no tanto por las l\u00e1grimas en s\u00ed, en el fondo irrelevantes, como por las censuras de los dem\u00e1s adultos. De hecho, con el pretexto de su amor por el ni\u00f1o, todos ellos daban rienda suelta a sus perversas inclinaciones por turnos, control\u00e1ndose y espi\u00e1ndose los unos a los otros.\n\n\nPero las c\u00f3leras de Giorgio eran de por s\u00ed espantosas. Con la astucia propia de esta clase de ni\u00f1os, sab\u00eda medir perfectamente el efecto de sus diversas represalias. Y utilizaba sus armas de la siguiente forma: para las peque\u00f1as contrariedades se echaba simplemente a llorar, pero eso s\u00ed, con unos sollozos que parec\u00edan romperle el pecho. En los asuntos m\u00e1s importantes, cuando la acci\u00f3n deb\u00eda prolongarse hasta la satisfacci\u00f3n del deseo negado, torc\u00eda el gesto y entonces no hablaba, no jugaba y se negaba a comer, lo que en menos de veinticuatro horas sum\u00eda a la familia en una gran consternaci\u00f3n. Cuando las circunstancias eran todav\u00eda m\u00e1s graves, sus t\u00e1cticas eran dos: o bien simulaba verse aquejado por misteriosos dolores en los huesos, no pareci\u00e9ndole aconsejables los dolores de cabeza y de vientre por el peligro de las purgas (y en la elecci\u00f3n de la enfermedad se revelaba su quiz\u00e1 inconsciente perfidia porque, con raz\u00f3n o sin ella, se pensaba enseguida en una par\u00e1lisis infantil); o bien, y tal vez era lo peor, se pon\u00eda a chillar: de su garganta sal\u00eda, ininterrumpido e inmutable, un grito extremadamente agudo, imposible de reproducir por los adultos, que perforaba el cerebro. Pr\u00e1cticamente era imposible de resistir. Giorgio se sal\u00eda r\u00e1pidamente con la suya, con el doble deleite de haber satisfecho su deseo y de ver a los mayores discutir, ech\u00e1ndose en cara los unos a los otros el haber exasperado al inocente.\n\n\nGiorgio no hab\u00eda tenido nunca una sincera inclinaci\u00f3n por los juguetes. Quer\u00eda que fueran muchos y preciosos por pura vanidad. Le gustaba llevar a casa a dos o tres amigos e impresionarlos. Uno tras otro iba sacando todos sus tesoros de un armarito que ten\u00eda cerrado con llave, en una progresi\u00f3n de magnificencia. Sus amigos se mor\u00edan de envidia y a \u00e9l le divert\u00eda humillarlos.\n\n\n\u2014No, t\u00fa no los toques, \u00a1tienes las manos sucias!\u2026 Te gusta, \u00bfverdad? Trae aqu\u00ed, trae aqu\u00ed, si no acabar\u00e1s por estropearlo\u2026 Dime, \u00bfa ti tambi\u00e9n te han regalado uno como \u00e9ste? (sabiendo de sobra que no era as\u00ed).\n\n\nPor la rendija de la puerta, sus padres y abuelos lo observaban tiernamente.\n\n\n\u2014\u00a1Qu\u00e9 gracioso! \u2014susurraban\u2014. Ya es un hombrecito\u2026 \u00a1Mirad qu\u00e9 orgullo tiene!\u2026 Cu\u00e1nto le importan sus juguetes, \u00a1sobre todo el osito que le ha regalado su abuela!\n\n\nComo si el hecho de ser celoso de sus juguetes fuera una virtud extraordinaria en un ni\u00f1o.\n\n\nUn d\u00eda, un conocido trajo a Giorgio un juguete maravilloso de Am\u00e9rica. Era un \u201ccami\u00f3n de leche\u201d, una reproducci\u00f3n perfecta de los camiones de leche de verdad: pintado de blanco y azul, con dos conductores uniformados que se pod\u00edan poner y quitar, las puertas de delante que se abr\u00edan y neum\u00e1ticos en las ruedas; dentro, amontonadas una encima de otra por medio de gu\u00edas especiales, hab\u00eda muchas cestitas de metal, cada una con ocho microsc\u00f3picas botellas selladas con un tap\u00f3n de esta\u00f1o. Y a los lados dos aut\u00e9nticos cierres met\u00e1licos de guillotina que, al abrirse, se enrollaban exactamente igual que los de verdad. Era sin duda el juguete m\u00e1s bonito y singular, y probablemente el m\u00e1s costoso, de todos los que pose\u00eda Giorgio.\n\n\nPues bien, una tarde, el abuelo, un coronel jubilado que por lo general no sab\u00eda en qu\u00e9 ocupar su tiempo, al pasar por delante del armario de los juguetes, tir\u00f3 por casualidad, como suele suceder, del pomo de la puerta. Not\u00f3 que ced\u00eda. Giorgio la hab\u00eda cerrado con llave como de costumbre, pero el otro batiente de la puerta, en el que encajaba el pestillo, no hab\u00eda sido fijado con los pasadores arriba y abajo, de modo que ambos batientes se abrieron.\n\n\nLos juguetes estaban perfectamente ordenados en cuatro estantes, todos relucientes y nuevos, porque Giorgio no los usaba casi nunca. \u00c9ste estaba fuera con Ida, sus padres tambi\u00e9n hab\u00edan salido y la abuela Elena hac\u00eda punto en la sala. Anna dormitaba en la cocina. La casa estaba tranquila y silenciosa. El coronel mir\u00f3 detr\u00e1s de s\u00ed, como un ladr\u00f3n. Despu\u00e9s, con un deseo acariciado desde hac\u00eda tiempo, extendi\u00f3 sus manos hacia el cami\u00f3n de la leche que resplandec\u00eda en la penumbra.\n\n\nEl abuelo lo coloc\u00f3 encima de la mesa, se sent\u00f3 y se dispuso a examinarlo. Pero hay una ley secreta que hace que, cuando un ni\u00f1o toca a escondidas alg\u00fan objeto de los mayores, \u00e9ste enseguida se rompe. Lo mismo sucede cuando los mayores se apoderan de un juguete que el ni\u00f1o ha podido manosear, con una energ\u00eda salvaje, durante meses sin llegar a estropearlo. Apenas el abuelo hubo alzado, con la delicadeza de un relojero, uno de los cierres laterales, se oy\u00f3 un \u201cclic\u201d: un listoncito de hojalata barnizada se desprendi\u00f3 y el perno sobre el que el cierre deber\u00eda de haberse enrollado oscil\u00f3 sin apoyo.\n\n\nLleno de zozobra, el viejo coronel se apresur\u00f3 a volver a ponerlo todo en su sitio. Pero las manos le temblaban. Tuvo claro que con su poca habilidad le ser\u00eda imposible reparar el da\u00f1o. Y no se trataba de una aver\u00eda oculta, f\u00e1cil de disimular. Una vez desgoznado el perno, el cierre dej\u00f3 de funcionar y colgaba completamente torcido.\n\n\nUna desesperada consternaci\u00f3n se apoder\u00f3 del hombre que un d\u00eda, al pie del Montello, hab\u00eda conducido a sus hombres en una carga suicida contra las ametralladoras de los austr\u00edacos. Un escalofr\u00edo le recorri\u00f3 la columna vertebral al o\u00edr una voz que parec\u00eda la del Juicio Final:\n\n\n\u2014V\u00e1lgame Dios, Antonio, \u00bfqu\u00e9 has hecho?\n\n\nEl coronel se volvi\u00f3. En el umbral de la puerta, inm\u00f3vil, su mujer, Elena, lo observaba con las pupilas dilatadas.\n\n\n\u2014Lo has roto, di, \u00bflo has roto?\n\n\n\u2014Qu\u00e9 dices, no est\u00e1\u2026 te ju\u2026 no es nada \u2014gimi\u00f3 el viejo militar, moviendo confusamente las manos en el absurdo intento de reparar el da\u00f1o.\n\n\n\u2014\u00bfY ahora qu\u00e9 vas a hacer? \u2014le apremi\u00f3 su mujer con ansiedad\u2014. \u00bfQu\u00e9 vas a hacer cuando Giorgio se entere?\n\n\n\u2014Te juro que apenas lo he tocado\u2026 deb\u00eda de estar ya roto\u2026 Yo no he hecho nada \u2014trat\u00f3 miserablemente de disculparse el coronel.\n\n\nY si en alg\u00fan momento se hab\u00eda hecho la ilusi\u00f3n de encontrar en su mujer cierta solidaridad moral, tal esperanza se desvaneci\u00f3 ante la indignaci\u00f3n de la anciana.\n\n\n\u2014Yo no he hecho nada, yo no he hecho nada, \u00a1pareces un papagayo!\u2026 \u00a1Si te parece se ha roto solo!\u2026 \u00a1Al menos haz algo! \u00a1Mu\u00e9vete en lugar de quedarte ah\u00ed como un est\u00fapido!\u2026 Giorgio puede llegar de un momento a otro\u2026 \u00bfY qui\u00e9n\u2026 (la voz no le sal\u00eda por la rabia)\u2026? \u00bfQui\u00e9n te manda abrir el armario de los juguetes?\n\n\nNo fue necesario nada m\u00e1s para que el coronel perdiera por completo la cabeza. Y para colmo de males era domingo, \u00a1imposible encontrar un operario que pudiera arreglar el camioncito! Mientras tanto, do\u00f1a Elena, seguramente para no verse implicada en el asunto, se fue. El coronel se sinti\u00f3 solo, abandonado, en la ingrata selva de la vida. La luz declinaba. Dentro de poco se har\u00eda de noche y Giorgio estar\u00eda de vuelta.\n\n\nCon el dogal al cuello, el abuelo corri\u00f3 entonces a la cocina en busca de un cordel, con el que, una vez levantado el techo del cami\u00f3n, consigui\u00f3 fijar los extremos del cierre, de tal forma que \u00e9ste qued\u00f3 m\u00e1s o menos arreglado. Evidentemente ya no se pod\u00eda abrir, pero al menos desde fuera no se notaba nada fuera de lo normal. Volvi\u00f3 a dejar el juguete en su sitio, cerr\u00f3 el armario y se retir\u00f3 a su estudio justo a tiempo. Tres largos y prepotentes timbrazos anunciaron el regreso del tirano.\n\n\n\u00a1Si al menos la abuela hubiera mantenido la boca cerrada! Pero no. A la hora del almuerzo, salvo el ni\u00f1o, todo el mundo estaba al corriente del desastre, incluidas las criadas. Hasta un ni\u00f1o menos astuto que Giorgio se habr\u00eda dado cuenta enseguida de que algo ins\u00f3lito y sospechoso flotaba en el ambiente. En dos o tres ocasiones, el coronel intent\u00f3 iniciar una conversaci\u00f3n. Pero nadie le secundaba.\n\n\n\u2014\u00bfQu\u00e9 os pasa? \u2014pregunt\u00f3 Giorgio con su habitual descaro\u2014. \u00bfOs ha comido la lengua el gato?\n\n\n\u2014Ah, \u00e9sta s\u00ed que es buena, dice que si nos ha comido la lengua el gato, \u00a1ja, ja! \u2014dijo el abuelo tratando heroicamente de que todo se transformara en una broma. Pero su risa se apag\u00f3 en el silencio.\n\n\nEl ni\u00f1o no hizo m\u00e1s preguntas. Con una sagacidad casi demon\u00edaca pareci\u00f3 entender que el malestar general ten\u00eda que ver con \u00e9l; que toda la familia, por alg\u00fan motivo desconocido, se sent\u00eda culpable, y que \u00e9l los ten\u00eda en sus manos.\n\n\n\u00bfC\u00f3mo pudo adivinarlo? \u00bfFue guiado por las ansiosas miradas de sus familiares que no se apartaban de \u00e9l ni un instante? \u00bfO hubo alguna delaci\u00f3n? El caso es que, finalizada la comida, Giorgio, con una sonrisita ambigua, fue al armario de los juguetes. Abri\u00f3 de par en par las puertas y permaneci\u00f3 durante un largo minuto en contemplaci\u00f3n, como si supiera que as\u00ed prolongaba la angustia del culpable. Luego, despu\u00e9s de haber hecho la elecci\u00f3n, sac\u00f3 el cami\u00f3n del mueble y, manteni\u00e9ndolo apretado bajo un brazo, fue a sentarse en un div\u00e1n, desde donde se puso a mirar fijamente a los mayores uno tras otro, sonriendo.\n\n\n\u2014\u00bfQu\u00e9 haces, Giorgino? \u2014dijo finalmente con voz d\u00e9bil el abuelo\u2014. \u00bfNo es hora de que te vayas a la cama?\n\n\n\u2014\u00bfA la cama? \u2014fue la evasiva respuesta del nieto, y su sonrisa se transform\u00f3 en una risa burlona.\n\n\n\u2014\u00bfY por qu\u00e9 no juegas entonces? \u2014se atrevi\u00f3 a decir el viejo, pareci\u00e9ndole que una cat\u00e1strofe r\u00e1pida era preferible a aquella agon\u00eda.\n\n\n\u2014No \u2014contest\u00f3 el ni\u00f1o despectivo\u2014, no tengo ganas de jugar.\n\n\nInm\u00f3vil, esper\u00f3 una media hora y entonces anunci\u00f3:\n\n\n\u2014Me voy a la cama \u2014y sali\u00f3 con el camioncito debajo del brazo.\n\n\nAquello se convirti\u00f3 en una man\u00eda. Durante el d\u00eda siguiente y el otro, Giorgio no se separ\u00f3 ni un instante del veh\u00edculo. Incluso quiso tenerlo a su lado en la mesa. Pero no jugaba con \u00e9l, no lo hac\u00eda rodar ni mostraba ninguna intenci\u00f3n de mirarlo por dentro.\n\n\nEl abuelo estaba en vilo.\n\n\n\u2014Giorgio \u2014dijo m\u00e1s de una vez\u2014, \u00bfpor qu\u00e9 nunca te separas de ese camioncito si luego no juegas con \u00e9l? \u00bfQu\u00e9 man\u00eda te ha dado? Vamos, ven aqu\u00ed, \u00a1ens\u00e9\u00f1ame las botellitas de leche!\n\n\nEn pocas palabras, le pesaba tanto el tormento de la espera que, sin importarle lo que sucediera despu\u00e9s, no ve\u00eda la hora en que su nietecito descubriera el desastre. Por otro lado, no se atrev\u00eda a confesar espont\u00e1neamente lo sucedido. Pero Giorgio se manten\u00eda firme.\n\n\n\u2014No, no me apetece. \u00bfNo es m\u00edo el cami\u00f3n? Entonces d\u00e9jame en paz.\n\n\nPor la noche, cuando Giorgio se iba a acostar, los mayores discut\u00edan.\n\n\n\u2014\u00a1D\u00edselo de una vez! \u00a1Todo antes que continuar as\u00ed! \u00a1Ya no vivimos por culpa de ese maldito cami\u00f3n!\n\n\n\u2014\u00bfMaldito? \u2014protestaba la abuela\u2014. No lo digas ni en broma\u2026 Es el juguete que m\u00e1s le gusta de todos. \u00a1Pobre ni\u00f1o!\n\n\nEl padre no le hac\u00eda caso.\n\n\n\u2014\u00a1D\u00edselo! \u2014repet\u00eda exasperado\u2014. T\u00fa que has luchado en dos guerras, \u00bfvas a tener el valor de dec\u00edrselo, s\u00ed o no?\n\n\nNo hizo falta. Al tercer d\u00eda, al ver aparecer a Giorgio con su camioncito, el abuelo no pudo contenerse.\n\n\n\u2014Vamos, Giorgio, \u00bfpor qu\u00e9 no lo haces andar un poco? \u00bfPor qu\u00e9 no juegas? \u00a1Me hace muy mal efecto verte siempre con ese chisme debajo del brazo!\n\n\nEntonces el ni\u00f1o frunci\u00f3 el ce\u00f1o disponi\u00e9ndose a cogerse una rabieta (\u00bfera sincero o interpretaba una comedia?). Despu\u00e9s empez\u00f3 a gritar y a sollozar.\n\n\n\u2014\u00a1Yo con mi cami\u00f3n hago lo que quiero! Dejadme en paz. Estoy harto, \u00bfentendido?\u2026 Puedo romperlo si quiero\u2026 Puedo pisotearlo\u2026 As\u00ed y as\u00ed, \u00a1mira!\n\n\nLevant\u00f3 su juguete con las dos manos, lo lanz\u00f3 al suelo con todas sus fuerzas, y despu\u00e9s se puso, en efecto, a pisotearlo, hasta que lo desfond\u00f3. Aplastado el techo, el camioncito se hizo pedazos y las botellitas se esparcieron por el suelo.\n\n\nEntonces Giorgio se detuvo de pronto, dej\u00f3 de gritar, se inclin\u00f3 a examinar una de las dos paredes interiores del veh\u00edculo y aferr\u00f3 un extremo del clandestino cordel puesto por el abuelo en el cierre. Furibundo, l\u00edvido, mir\u00f3 a su alrededor.\n\n\n\u2014\u00bfQui\u00e9n ha sido? \u2014balbuce\u00f3\u2014. \u00bfQui\u00e9n lo ha tocado? \u00bfQui\u00e9n lo ha roto?\n\n\nEl abuelo, el viejo combatiente, se adelant\u00f3 un poco encorvado.\n\n\n\u2014Oh, Giorgino, vida m\u00eda \u2014suplic\u00f3 la madre\u2014. S\u00e9 bueno. El abuelo no lo ha hecho a prop\u00f3sito, cr\u00e9eme. \u00a1Perd\u00f3nale, Giorgino m\u00edo!\n\n\nIntervino tambi\u00e9n la abuela.\n\n\n\u2014Ah, no, criatura, tienes raz\u00f3n\u2026 Toma y toma, pega al abuelo malo que te rompe todos los juguetes\u2026 Pobre inocente. Le rompen los juguetes y luego adem\u00e1s quieren que sea bueno, pobrecito. \u00a1Toma y toma, pega al abuelo malo!\n\n\nDe pronto Giorgio volvi\u00f3 a quedarse tranquilo. Mir\u00f3 lentamente las caras ansiosas que lo rodeaban y una sonrisa reapareci\u00f3 en sus labios.\n\n\n\u2014Si ya lo dec\u00eda yo \u2014dijo la madre\u2014. \u00a1Siempre he dicho que es un \u00e1ngel! \u00a1Giorgio ha perdonado al abuelo! \u00a1Mirad, es un bendito!\n\n\nPero el ni\u00f1o volvi\u00f3 a examinarlos uno a uno: al padre, la madre, el abuelo, la abuela y las dos criadas.\n\n\n\u2014Mirad, es un bendito\u2026 \u00a1mirad, es un bendito! \u2014canturre\u00f3 imit\u00e1ndola. Dio una patada a la carcasa de su cami\u00f3n, que fue a chocar contra la pared, y despu\u00e9s se ech\u00f3 a re\u00edr fren\u00e9ticamente. Re\u00eda como un descosido.\n\n\n\u2014\u00a1Mirad, es un bendito! \u2014repiti\u00f3 socarr\u00f3n, saliendo del cuarto.\n\n\nAterrorizados, los mayores callaron.\n\n\n*FIN*\n\n\n\n\n\u201cIl bambino tiranno\u201d,\n\n\nCorriere della Sera,\n 1951\n\n"}