{"metadata": {"length": 20595, "words": 3598, "reading_time_min": 17.99}, "text": "Era la hora del anochecer, de uno de los \u00faltimos d\u00edas de oto\u00f1o. La Feria Comarcal de Winesburgo hab\u00eda atra\u00eddo al pueblo una gran muchedumbre de gentes del campo. El d\u00eda hab\u00eda sido despejado y la noche se presentaba tibia y agradable. Las carretas que pasaban por Trunion Pike, en donde la carretera se extend\u00eda, al salir, de la ciudad, por entre campos de fresales, cubiertos ahora de oscuras hojas secas, levantaban nubes de polvo. Los ni\u00f1os, arrebujados como peque\u00f1as pelotas, dorm\u00edan encima de la paja extendida dentro de los carros. Sus cabellos estaban cubiertos de polvo, y sus dedos sucios y pegajosos. El polvo se cern\u00eda sobre los campos; y el sol, al ocultarse, lo te\u00f1\u00eda con vivo resplandor.\n\n\nLa muchedumbre llenaba las tiendas y las aceras de la calle principal de Winesburgo. Se ech\u00f3 encima la noche, relincharon los caballos, los dependientes de las tiendas iban y ven\u00edan como locos, los ni\u00f1os se extraviaban y romp\u00edan a berrear, y todo un pueblo de Norteam\u00e9rica trabajaba desesperadamente por divertirse.\n\n\nEl joven George Willard se abri\u00f3 paso por entre la muchedumbre que llenaba Main Street, se escondi\u00f3 en la escalera del consultorio del doctor Reefy y observ\u00f3 desde all\u00ed a la gente. Examinaba con ojos febriles las caras que desfilaban bajo las luces de los almacenes. Pugnaban por irrumpir en su cerebro toda clase de pensamientos, pero \u00e9l no quer\u00eda pensar. Golpeaba impaciente con los pies en las escaleras de madera y miraba inquisitivamente a todas partes. \u201cBueno, \u00bfser\u00e1 capaz ella de no apartarse de \u00e9l en todo el d\u00eda? \u00bfMe habr\u00e1 hecho esperar in\u00fatilmente todo este rato?\u201d, murmur\u00f3.\n\n\nGeorge Willard, el muchacho de aquel pueblo de Ohio, se hac\u00eda r\u00e1pidamente hombre y empezaba a pensar de distinta manera que hasta entonces. Hab\u00eda andado todo el d\u00eda entre aquella masa humana de las ferias, con un sentimiento de soledad en el alma. Pronto iba a abandonar Winesburgo para marchar a una ciudad, donde esperaba colocarse en alg\u00fan peri\u00f3dico; ten\u00eda la sensaci\u00f3n de ser una persona mayor. Aquel estado de \u00e1nimo suyo era propio de hombre e impropio de un muchacho. Sent\u00edase viejo y un poco cansado. Se despertaban en \u00e9l los recuerdos. Cre\u00eda que su nuevo sentimiento de madurez lo apartaba del mundo, haciendo de \u00e9l una figura casi tr\u00e1gica. Hubiera querido que alguien fuese capaz de comprender la sensaci\u00f3n que lo dominaba despu\u00e9s de la muerte de su madre.\n\n\nLlega para todos los muchachos un momento en cl que se vuelven a contemplar su vida pasada. Es tal vez ese momento en que cruzan la l\u00ednea que los separa de la edad viril. El muchacho pasea por las calles de su pueblo. Piensa en su porvenir, en el papel que representar\u00e1 en el mundo. Despi\u00e9rtase en \u00e9l ambiciones y arrepentimientos. De pronto ocurre algo imprevisto; se detiene debajo de un \u00e1rbol y permanece como a la espera de que alguien le llame por su nombre. Se deslizan en su conciencia sombras de cosas pasadas; las voces del exterior le susurran un mensaje que le habla de las limitaciones de la vida. La seguridad absoluta que ten\u00eda en su porvenir se trueca en una absoluta inseguridad. Si es un muchacho de imaginaci\u00f3n, cae derribada delante de \u00e9l una puerta y se le presenta ante la vista, por vez primera, el panorama del mundo; ve, como si desfilaran ante \u00e9l en procesi\u00f3n, las incontables figuras de hombres que hasta aquel momento han salido de la nada, han vivido sus vidas y han vuelto a desaparecer en la nada. La tristeza de lo falaz ha ca\u00eddo sobre el muchacho. Se mira at\u00f3nito a s\u00ed mismo como una simple hoja que el viento arrastra por las calles de su pueblo. Comprende que, a pesar de toda la seguridad vocinglera con que hablan sus compa\u00f1eros, est\u00e1 condenado a vivir y morir en la incertidumbre; que es una cosa arrastrada por el viento, una cosa destinada a agotarse, como el trigo, bajo los rayos del sol. Se estremece y mira en torno suyo. Los dieciocho a\u00f1os que \u00e9l ha vivido parecen solo un momento, el tiempo de una respiraci\u00f3n en la larga marcha de la Humanidad. Escucha ya la llamada de la muerte. Y anhela desde lo m\u00e1s hondo de su coraz\u00f3n acercarse a otro ser humano, tocar con sus manos a otra persona, sentir la caricia de otras manos. Si prefiere que esas manos sean las de una mujer es porque cree que la mujer ser\u00e1 afectuosa, que le comprender\u00e1. Eso es lo que quiere sobre todo: comprensi\u00f3n.\n\n\nCuando lleg\u00f3 para George Willard ese momento de desenga\u00f1o, su pensamiento se volvi\u00f3 hacia Helen White, la hija del banquero de Winesburgo. Se hab\u00eda dado cuenta en todo momento de que aquella joven se hac\u00eda mujer a la par que \u00e9l entraba en la virilidad. Cuando \u00e9l ten\u00eda dieciocho a\u00f1os, sali\u00f3 cierta noche de verano a pasear con ella por el campo y se dej\u00f3 llevar, en presencia suya, de un impulso de fanfarroner\u00eda; quiso aparecer grande e importante ante sus ojos. Ahora llevaba otras intenciones al pretender verse con ella. Quer\u00eda hablarle de los nuevos pensamientos de que se sent\u00eda inspirado. Se hab\u00eda esforzado, cuando nada sab\u00eda \u00e9l acerca de la hombr\u00eda, en hacer que ella lo tomase por un hombre, y ahora quer\u00eda estar a su lado para hacerle comprender el cambio que se hab\u00eda operado, seg\u00fan \u00e9l cre\u00eda, en su naturaleza.\n\n\nTambi\u00e9n Helen White hab\u00eda llegado a un per\u00edodo de transformaci\u00f3n. Lo que George sent\u00eda, tambi\u00e9n lo sent\u00eda ella a la manera de una mujer joven. Ya no era una ni\u00f1a, y ansiaba alcanzar la gracia y la belleza de la mujer hecha. Hab\u00eda llegado de Cleveland, en uno de cuyos colegios estudiaba, para pasar un d\u00eda en la feria. Tambi\u00e9n ella empezaba a tener recuerdos. Durante el d\u00eda permaneci\u00f3 sentada en la gran tribuna, acompa\u00f1ada por un joven, uno de los profesores adjuntos del colegio, que era hu\u00e9sped de su madre. Era un joven algo pedante, y ella comprendi\u00f3 en seguida que no era el hombre que a ella le hac\u00eda falta. Estaba satisfecha de que la viesen en la feria con \u00e9l, porque vest\u00eda bien y era forastero. Estaba segura de que la sola presencia del joven producir\u00eda impresi\u00f3n. Sent\u00edase feliz durante el d\u00eda, pero cuando se hizo de noche empez\u00f3 a estar desasosegada. Quer\u00eda alejar de all\u00ed al profesor, escapar ele su presencia. Mientras estuvieron sentados en la gran tribuna y vio clavados en ella los ojos de sus antiguas compa\u00f1eras de escuela, mostr\u00f3se Helen tan atenta con su acompa\u00f1ante que \u00e9ste fue interes\u00e1ndose. \u201cUn hombre de ciencia necesita dinero. Yo deber\u00eda casarme con una mujer que tuviese dinero\u201d, cavilaba.\n\n\nHelen White iba pensando en George Willard en el momento mismo en que \u00e9ste se paseaba, t\u00e9trico, entre la multitud. Se acordaba de la noche de verano en que hab\u00edan salido juntos, y quer\u00eda volver a pasear en su compa\u00f1\u00eda. Pensaba que los meses que ella hab\u00eda pasado en la ciudad, asistiendo a teatros y viendo caminar a las grandes multitudes por las anchas avenidas iluminadas, la hab\u00edan cambiado profundamente. Quer\u00eda que \u00e9l sintiese y se diese cuenta de la transformaci\u00f3n de su naturaleza.\n\n\nMirando las cosas razonablemente, la noche que hab\u00edan pasado juntos y que tan grabada hab\u00eda quedado en la memoria del joven como en la de la mujer, se hab\u00eda pasado de una manera bastante tonta. Salieron fuera de la ciudad y caminaron por un camino vecinal; luego se detuvieron junto a una vallado, cerca de un campo de trigo verde, y George se quit\u00f3 la americana y se la colg\u00f3 del brazo. \u201cBueno, hasta ahora no me he movido de Winesburgo, eso es; todav\u00eda no he salido de aqu\u00ed; pero ya voy haci\u00e9ndome mayor -dijo-. He le\u00eddo muchos libros y he pensado mucho. Voy a intentar ser algo en la vida.\u201d\n\n\n\u201cVer\u00e1s \u2014explic\u00f3\u2014; no es eso lo que quer\u00eda decir. Lo mejor ser\u00eda, tal vez, que me callase.\u201d\n\n\nEl muchacho, completamente turbado, apoy\u00f3 su mano en el brazo de la joven. Le temblaba la voz. Retrocedieron por el mismo camino, hacia el pueblo. Y en su desesperaci\u00f3n, solt\u00f3 George esta balandronada: \u201cYo he de llegar a ser un gran hombre, el m\u00e1s grande de cuantos han vivido en Winesburgo. Te necesito, aunque no s\u00e9 como. Es posible que no tenga derecho a dec\u00edrtelo. Y yo quisiera que t\u00fa fueses una mujer distinta de las dem\u00e1s. Ya me comprendes. No soy yo quien debe dec\u00edrtelo. Que seas una espl\u00e9ndida mujer-. Eso es lo que quiero.\u201d\n\n\nLa voz del muchacho se apag\u00f3, y los dos regresaron en silencio al pueblo, pasando por Main Street para ir a casa de Helen. Ya en el portal, hizo George un esfuerzo para decir alguna cosa ele efecto. Se acord\u00f3 de los discursos que se tra\u00eda preparados, pero le parecieron completamente in\u00fatiles. \u201cYo pensaba -yo sol\u00eda pensar-, yo ten\u00eda la idea de que t\u00fa te casar\u00edas con Seth Richmond. Ahora ya s\u00e9 que no\u201d, fue todo lo que acert\u00f3 a decir cuando ella atraves\u00f3 el portal y se dirigi\u00f3 hacia la puerta de entrada de su casa.\n\n\nEn este tibio anochecer de oto\u00f1o, de pie en la escalera y mirando a la gente que pasaba por Main Street, record\u00f3 George la conversaci\u00f3n aqu\u00e9lla junto al campo de verde trigo, y sinti\u00f3 verg\u00fcenza del papel que hab\u00eda representado.\n\n\nLa gente iba y ven\u00eda por la calle como ganado confinado dentro de una empalizada. Los carricoches y carros obstru\u00edan casi por completo la estrecha calzada. Tocaba una banda, y los muchacos peque\u00f1os corr\u00edan por la acera, meti\u00e9ndose por entre las piernas de los hombres; muchachos j\u00f3venes de rostros rubicundos caminaban torpemente con j\u00f3venes cogidas de su brazo. En una sala situada encima de un almac\u00e9n, en la que iba a darse baile, templaban los violinistas sus instrumentos. Sus notas cortadas ca\u00edan por la ventana abierta y flotaban por entre el murmullo de voces y los bramidos de las cornetas de la banda. Aquella mezcolanza de ruidos excit\u00f3 los nervios del joven Willard. En todas partes, por todos lados, lo rodeaba una sensaci\u00f3n de muchedumbre, de vida en ebullic\u00ed\u00f3n. Quer\u00eda escapar de all\u00ed, a un lugar en que se sintiese solo y pudiese meditar. \u201cQue siga con ese joven, si tal es su deseo. \u00bf Por qu\u00e9 he de preocuparme? \u00bf No es lo mismo para m\u00ed?\u201d, exclam\u00f3 gru\u00f1onamente, y se lanz\u00f3 por Main Street; al llegar a la tienda de ultramarinos de Hern dobl\u00f3 por una calle lateral.\n\n\nGeorge sent\u00edase tan completamente solo y abatido que sent\u00eda impulsos de llorar; pero el orgullo le oblig\u00f3 a seguir adelante, balanceando los brazos. Lleg\u00f3 hasta las caballerizas de alquiler de Wesley Moyer y se detuvo en la oscuridad a escuchar lo que dec\u00eda un grupo de hombres que estaban conversando acerca de la carrera que hab\u00eda ganado aquella tarde en la feria el gara\u00f1\u00f3n de Wesley, Tony Tip; se hab\u00eda reunido un gran n\u00famero de personas frente a las caballerizas, v Wesley se paseaba por delante del grupo, dandose importancia y fanfarroneando. Ten\u00eda en la mano un l\u00e1tigo y no cesaba de dar golpes en el suelo con \u00e9l. A la luz de la l\u00e1mpara se ve\u00eda c\u00f3mo saltaba a cada golpe una nubecilla de polvo. \u201cPor todos los diablos, callaos \u2014exclam\u00f3 Wesley\u2014. Yo no ten\u00eda miedo; desde el primer momento estaba seguro de vencerlo. No ten\u00eda miedo.\u201d\n\n\nAquellas fanfarronadas del tratante Moyer habr\u00edan despertado el inter\u00e9s de George Willard de haber estado en su ordinaria situaci\u00f3n de \u00e1nimo, pero en esta ocasi\u00f3n lo pusieron furioso. Dio media vuelta y se alej\u00f3 por la calle. \u201cViejo fanfarr\u00f3n \u2014mascull\u00f3 entre dientes\u2014. \u00bfPor qu\u00e9 ser\u00e1 tan jactancioso? \u00bfPor qu\u00e9 no se callar\u00e1?\u201d\n\n\nGeorge se meti\u00f3 por un solar vac\u00edo, y en su precipitaci\u00f3n tropez\u00f3 y se cay\u00f3 encima de un mont\u00f3n de trastos viejos. Un clavo que sobresal\u00eda de un barril desfondado le rasg\u00f3 el pantal\u00f3n. Sent\u00f3se en el suelo y empez\u00f3 a echar maldiciones. Arregl\u00f3 el rasgu\u00f1o del pantal\u00f3n con un alfiler, se levant\u00f3 y sigui\u00f3 adelante. \u201cLo que voy a hacer es ir a casa de Helen White. Ir\u00e9 derecho all\u00ed. Dir\u00e9 que quiero hablar con ella. Me ir\u00e9 all\u00ed sin rodeos y me sentar\u00e9 a esperar\u201d, se dijo, al mismo tiempo que saltaba por una empalizada y echaba a correr.\n\n\n\u00a0\n\n\n* * *\n\n\n\u00a0\n\n\nHelen se hallaba en la terraza de la casa del banquero White, desasosegada y distra\u00edda. El profesor adjunto estaba sentado entre la madre y la hija. Su conversaci\u00f3n aburr\u00eda a la joven. Aunque tambi\u00e9n el joven profesor se hab\u00eda educado en un pueblo de Ohio, empez\u00f3 a darse aires de hombre de ciudad. Quer\u00eda aparentar cosmopolitismo. \u201cMe encanta esta oportunidad que ustedes me han dado de estudiar el ambiente de donde salen la mayor parte de nuestros j\u00f3venes \u2014exclam\u00f3\u2014. Ha sido usted muy amable, se\u00f1ora White, al invitarme y pasar aqu\u00ed el d\u00eda de hoy.\u201d Se volvi\u00f3 hacia Helen y se ech\u00f3 a re\u00edr. \u201c\u00bfSe halla la vida de usted ligada todav\u00eda a la vida de este pueblo? \u00bfHay aqu\u00ed personas por las que usted se interesa?\u201d, dijo. Aquella voz son\u00f3 en los o\u00eddos de la joven como cosa afectada y aburrida.\n\n\nHelen se levant\u00f3 y se meti\u00f3 dentro. Se detuvo junto a la puerta que daba al jard\u00edn en la parte trasera de la casa y se puso a escuchar. Su madre empezaba a decir: \u201cNo hay en este pueblo un partido conveniente para una joven de las condiciones de Helen.\u201d\n\n\nHelen baj\u00f3 corriendo un tramo de escaleras y sali\u00f3 al jard\u00edn. Se detuvo temblorosa en la oscuridad. Ten\u00eda la sensaci\u00f3n de que el mundo estaba lleno de gentes sin sentido, que no hac\u00edan m\u00e1s que hablar. Presa de ardiente ansiedad, sali\u00f3 corriendo por el portal del jard\u00edn y, doblando una esquina junto a las caballerizas del banquero, sigui\u00f3 por una peque\u00f1a calle lateral. \u201c\u00a1George! \u00bfD\u00f3nde est\u00e1s?\u201d, exclam\u00f3 dominada por una exaltaci\u00f3n nerviosa. Se detuvo y se apoy\u00f3 contra un \u00e1rbol, rompiendo a re\u00edr hist\u00e9ricamente. George Willard se acercaba por la peque\u00f1a calle oscura, hablando solo: \u201cVoy a meterme de rond\u00f3n en su casa. Entrar\u00e9, sin m\u00e1s, y me sentar\u00e9\u201d, iba diciendo, y en aquel momento tropez\u00f3 con ella. Se detuvo y se le qued\u00f3 mirando atontado. \u201cVen\u201d, dijo, y la cogi\u00f3 de la mano. Caminaban bajo los \u00e1rboles de la calle con las cabezas inclinadas. Las hojas secas rechinaban bajo sus pies. George pensaba en lo que le convendr\u00eda hacer y decir, ahora que la hab\u00eda encontrado.\n\n\n\u00a0\n\n\n* * *\n\n\n\u00a0\n\n\nAl extremo superior del campo de la feria de Winesburgo hay una vieja tribuna destartalada. Jam\u00e1s le dieron una mano de pintura, y las tablas se hallaban torcidas y deformadas. El campo de la feria est\u00e1 en lo alto de una peque\u00f1a colina que se eleva en el valle del Wine Creek, y por la noche se distinguen desde la tribuna, m\u00e1s all\u00e1 de unos trigales, las luces del pueblo, que parecen brillar sobre el fondo del firmamento.\n\n\nGeorge y Helen subieron hacia lo alto de la colina por un sendero que pasaba junto al dep\u00f3sito de aguas corrientes. La sensaci\u00f3n de soledad y aislamiento que se hab\u00eda apoderado del joven en las calles llenas de concurrencia, quedaba ahora disipada, e intensificada al mismo tiempo con la presencia de Helen. Y lo que el joven sent\u00eda reflej\u00e1base en ella.\n\n\nEn todos los j\u00f3venes hay dos fuerzas que se entrechocan. El peque\u00f1o animal impetuoso e irreflexivo lucha contra el ser que piensa y recuerda; y aquel estado de \u00e1nimo, propio de un ser de m\u00e1s edad y m\u00e1s desenga\u00f1ado, se hab\u00eda apoderado de George Willard. Helen, que lo adivinaba, caminaba a su lado llena de respeto. Cuando llegaron a la tribuna se encaminaron hasta la fila m\u00e1s alta y tomaron asiento en uno de los bancos.\n\n\nVisitando el campo de la feria, en los alrededores de cualquier pueblo del Medio Oeste, durante la noche que sigue al d\u00eda de su celebraci\u00f3n, se experimenta una sensaci\u00f3n inolvidable. Se ven por todas partes, sombras, no de difuntos, sino de personas vivientes. Durante el d\u00eda se han congregado aqu\u00ed las gentes del pueblo y de la regi\u00f3n circunvecina. Dentro del vallado del campo se han reunido los granjeros con sus mujeres y sus hijos, y todas las personas que viven en los centenares de peque\u00f1as casas de madera. Se han re\u00eddo las j\u00f3venes y han hablado de sus asuntos los hombres barbudos. Aquel lugar estaba rebosante de vida. Bull\u00eda y reventaba de vida; pero ha llegado la noche y la vida se ha retirado de all\u00ed. El silencio es casi aterrador. Si una persona de naturaleza reflexiva se oculta y permanece en silencio junto al tronco de un \u00e1rbol, todo lo que hay de reflexivo en su temperamento se intensifica. Se estremece al pensar en la futilidad de la vida; y al mismo tiempo, si se trata de un habitante de aquel pueblo, siente hacia ellos un amor tan intenso que le salen las l\u00e1grimas a los ojos. George Willard estaba sentado junto a Helen, en la oscuridad, bajo el techo de la tribuna, y sent\u00eda con gran viveza su propia insignificancia dentro del sistema de la vida. Lejos ya del pueblo, en donde se irritaba por la presencia de aquellas gentes que iban y ven\u00edan agitadas y atareadas por una multitud de negocios, desapareci\u00f3 su irritabilidad. La presencia de Helen le serv\u00eda de t\u00f3nico y sedante. Parec\u00eda como si aquella mano de mujer le ayudase a poner a punto minuciosamente la maquinaria de su vida. Empez\u00f3 a pensar, casi con reverencia, en aquellas gentes del pueblo en donde hab\u00eda vivido siempre. Sent\u00eda un gran respeto por Helen. Quer\u00eda amarla y ser amado por ella; pero en aquel momento no quer\u00eda sentirse conturbado por la mujer que hab\u00eda surgido en ella. La cogi\u00f3 de la mano en la oscuridad; y, cuando ella se le aproxim\u00f3, George le pas\u00f3 la mano por la espalda. Empez\u00f3 a soplar el viento, y ella empez\u00f3 a tiritar. George concentr\u00f3 toda su energ\u00eda, intentado comprender y hacerse cargo de aquel estado de \u00e1nimo que se hab\u00eda adue\u00f1ado de \u00e9l. All\u00e1 en la oscuridad, en aquella eminencia, se abrazaban estrechamente dos \u00e1tomos humanos, pose\u00eddos de una extra\u00f1a sensibilidad, y esperaban. Los dos ten\u00edan el mismo pensamiento. \u201cYo he venido a este lugar solitario, y aqu\u00ed est\u00e1 este otro.\u201d Tal era en sustancia lo que sent\u00edan.\n\n\nAquel d\u00eda, de tanta concurrencia en Winesburgo, se hab\u00eda esfumado hasta convertirse en una de las largas noches de fines de oto\u00f1o. Los caballos de las granjas se alejaban trotando por los solitarios caminos vecinales, arrastrando cada cual su parte correspondiente de gente fatigada. Los dependientes empezaron a retirar de las aceras las muestras y fueron cerrando las puertas de las tiendas. En el teatro de la Opera se hab\u00eda congregado una gran muchedumbre para presenciar la representaci\u00f3n. M\u00e1s all\u00e1, en Main Street los violinistas, una vez templados los instrumentos, trabajaban y sudaban para que los pies de la juventud volasen sin descanso por el suelo del sal\u00f3n de baile.\n\n\nHelen White y George Willard permanecieron callados en la oscuridad de la tribuna. De ver, en cuando se romp\u00eda el encanto que los ten\u00eda embargados y se volv\u00edan para mirarse a los ojos. Se besaban, pero este \u00edmpetu no duraba mucho. Al extremo m\u00e1s elevado del campo de la feria hab\u00eda media docena de hombres cuidando los caballos que hab\u00edan corrido aquella tarde. Hab\u00edan hecho una hoguera y calentaban en ella ollas de agua. Solo se distingu\u00edan sus piernas cuando se mov\u00edan, a la luz de las llamas. Cuando soplaba el viento danzaban locamente las peque\u00f1as lenguas de fuego.\n\n\nGeorge y Helen se levantaron y fueron caminando en medio de la oscuridad. Siguieron por un sendero que pasaba junto a un trigal no cortado todav\u00eda. El viento susurraba entre las secas espigas. Aquel encanto que los embargaba se quebr\u00f3 un momento durante su regreso al pueblo. Cuando llegaron a la cima de la colina del dep\u00f3sito de aguas se detuvieron junto a un \u00e1rbol y George volvi\u00f3 a poner sus manos en los hombros de la joven. Ella le abraz\u00f3 ardientemente, pero los dos contuvieron r\u00e1pidamente aquel impulso; dejaron de besarse y permanecieron un poco apartados. Creci\u00f3 en ellos el sentimiento de mutuo respeto. Sinti\u00e9ronse cohibidos y, para librarse de esa penosa sensaci\u00f3n, se dejaron dominar por los \u00edmpetus animales de la juventud. Estallaron en risas y empezaron a darse empujones y a tironear el uno del otro. Amansados y purificados en cierto sentido por aquel estado de \u00e1nimo de que hab\u00edan estado pose\u00eddos, no fueron ya hombre y mujer, ni muchacho ni muchacha, sino dos peque\u00f1os animales impetuosos.\n\n\nY de esta manera descendieron por la ladera de la colina. Jugueteaban en la oscuridad corno dos magn\u00edficos seres j\u00f3venes, en un mundo joven. Una de las veces en que corr\u00edan como locos, tropez\u00f3 Helen con George, y \u00e9ste cay\u00f3 al suelo, braceando y gritando. Rod\u00f3 colina abajo entre grandes risotadas; Helen corri\u00f3 tras \u00e9l. Se detuvo un momento en la oscuridad. No es posible saber cu\u00e1les fueron los pensamientos de mujer que cruzaron entonces por su mente; cuando estuvieron al pie de la colina y se acerc\u00f3 ella al muchacho, le cogi\u00f3 del brazo y camin\u00f3 a su lado en medio de un silencio lleno de dignidad. Ni uno ni otro habr\u00edan podido explicar, por alguna raz\u00f3n desconocida, que aquella noche sin palabras les hab\u00eda proporcionado lo que ellos buscaban. Hombre o muchacho, mujer o ni\u00f1a, se hab\u00edan compenetrado durante un momento de aquello que hace posible que los hombres y mujeres que han llegado a la madurez de su vida vivan en el mundo moderno.\n\n\n*FIN*\n\n\n\n\n\u201cSophistication\u201d,\n\n\nWinesburg, Ohio, \n1919\n\n"}