{"metadata": {"length": 13533, "words": 2347, "reading_time_min": 11.735}, "text": "Era D. Narciso un enfermo de mucho cuidado; entend\u00e1monos, porque la frase es de doble sentido. No digo que estuviera enfermo de mucho cuidado\u2026 Tampoco esto va bien. Si estaba enfermo de mucho cuidado, ya lo creo; muy grave; sobre todo porque empeoraba, empeoraba y no se pod\u00eda acertar con el remedio, ni hab\u00eda seguridad alguna en el diagn\u00f3stico. Pero lo que yo quer\u00eda decir primero no se refiere a la gravedad y rareza del mal, sino a la condici\u00f3n personal de D. Narciso, que era un enfermo de mucho cuidado\u2026 como hay toros de mucho cuidado tambi\u00e9n, ante los cuales el torero necesita tomar bien las medidas a las distancias, y a los quiebros, y al tiempo, para no verse en la cuna. El m\u00e9dico era a don Narciso lo que el torero a esos toros; porque don Narciso, hombre nervios\u00edsimo, fil\u00f3sofo esc\u00e9ptico y aficionado a leer de todo, y por contra aprensivo, como todos los muy enamorados de la propia, preciosa existencia, le pon\u00eda las peras a cuarto al doctor, discut\u00eda con \u00e9l, le exig\u00eda conocimientos exactos a lo que a \u00e9l le pasaba por dentro, conocimientos que el doctor estaba muy lejos de poseer; y con las voces t\u00e9cnicas m\u00e1s precisas le combat\u00eda, le presentaba objeciones, y, en fin, le desesperaba. Lo peor era que, acostumbrado don Eleuterio, el m\u00e9dico, a la mala man\u00eda de hablar delante de sus enfermos legos en los t\u00e9rminos del arte, porque as\u00ed ni \u00e9l ment\u00eda ocultando la gravedad del mal, ni los enfermos se alarmaban demasiado, porque no le entend\u00edan, a veces se le escapaba delante de D. Narciso alguna de esas palabrotas poco tranquilizadoras para quien las entiende; y el paciente, erudito, siquiera fuese a la violeta, pon\u00eda el grito en el cielo, se alborotaba, y si no ped\u00eda la Extremaunci\u00f3n no era por falta de miedo. Hab\u00eda que tranquilizarle, mentir, establecer distingos, en fin, sudar ciencia y paciencia; y no para curarle, sino para que se volviese a sus casillas. Don Eleuterio aguantaba todas estas impertinencias porque el parroquiano o cliente era de oro por lo bien que pagaba, y, adem\u00e1s, hombre influyente y de mucho viso; en fin, no se le pod\u00eda plantar, pese a todas sus\u2026 cosas, como las llamaba el m\u00e9dico por no insultar al otro.\n\n\nY no val\u00eda que las palabras terminadas en itis o en algia, y otras no menos b\u00e1rbaras, fuesen de uso completamente nuevo, acabadas de componer por un sabio, autor de libro o art\u00edculo de revista, o de laboratorio; todo lo comprend\u00eda el entrometido, porque como picaba tambi\u00e9n en las lenguas sabias, no era manco en la griega, o mejor, no era deslenguado; y en seguida, anhelante, preocupad\u00edsimo, analizaba los componentes del terminacho flamante, y sea con ayuda del l\u00e9xico, o sin ella, sacaba en limpio\u2026 que \u00e9l ten\u00eda el h\u00edgado mechado, como dice un personaje de Zarag\u00fceta, o el ri\u00f1\u00f3n cubierto\u2026 de \u00falceras, o cualquier otra barbaridad.\n\n\nAquello era un purgatorio. La familia de don Narciso pagaba el suplemento de las pejigueras que ten\u00eda que aguantar el facultativo. Al cual le costaba m\u00e1s trabajo hacerse respetar, en nombre de la autoridad de la ciencia, porque, cuando estaba sano el amigo D. Narciso, sol\u00edan convenir, sobre todo si tomaban juntos a la saz\u00f3n caf\u00e9 y copa, en que la Medicina est\u00e1 en la edad de piedra, y puede que nunca alcance la de oro. Los dos hac\u00edan alarde de su escepticismo terap\u00e9utico; el m\u00e9dico muy vano porque cre\u00eda que era un acto de imparcialidad sublime y de abnegaci\u00f3n el confesar \u00e9l semejante bancarrota (palabra de moda en las ciencias), contra lo que le aconsejaban sus intereses; y el otro muy hueco porque luc\u00eda su erudici\u00f3n trayendo a cuento a los ilustres varones que hab\u00edan renegado de m\u00e9dicos y medicinas. \u00abC\u00f3mo dijo Moli\u00e8re\u2026 Seg\u00fan Montaigne\u2026 Dijo Quevedo\u00bb, etc., etc.\n\n\nY claro, cuando hab\u00eda que agarrarse a un clavo ardiendo, recurrir a la Medicina, porque D. Narciso se iba por la posta, \u00bfcon qu\u00e9 cara le hablaba don Eleuterio de la eficacia de las recetas ni a\u00fan de la probabilidad de los diagn\u00f3sticos? \u00bfNo hab\u00edan convenido en que el juego fatal de los fen\u00f3menos naturales era demasiado complejo para que el hombre pudiera tener la pretensi\u00f3n de penetrar en su enmara\u00f1ada urdimbre? Todo iba a dar a la qu\u00edmica\u2026 y la verdadera qu\u00edmica estaba en mantillas.\n\n\nNo se sab\u00eda si exist\u00edan los \u00e1tomos; lo probable era que no; y sin embargo, los \u00e1tomos; eran indispensables para la qu\u00edmica\u2026 y ni a\u00fan esto era ya muy seguro, seg\u00fan las recientes disputas de Ostwald, Cornu, etc. De modo que todo estaba en el aire\u2026 todo se reduc\u00eda a conjeturas, a hip\u00f3tesis\u2026 \u00a1y a don Narciso le llevaban los demonios, porque no quer\u00eda que el important\u00edsimo negocio de su r\u00e1pida curaci\u00f3n dependiese de nada hipot\u00e9tico\u2026 \u00abO ji o ja\u00bb, gritaba \u00e9l; ji era la muerte y ja la salud. Y aunque dec\u00eda ji o ja, al m\u00e9dico no le permit\u00eda decir m\u00e1s que ja. Y ja dec\u00eda D. Eleuterio a rega\u00f1adientes, porque le gustaba ser claro. Pero en diciendo \u00e9l ja (la salud, sin duda), se irritaba el otro, y exclamaba:\n\n\n-\u00bfUsted qu\u00e9 sabe? A m\u00ed no se me enga\u00f1a. Tanto cree usted en esas p\u00f3cimas como yo; ni usted ni nadie sabe lo que yo tengo en el bazo, ni lo que puede sobrevenir en el h\u00edgado\u2026 \u2013 \u00a1Todo es farsa! Usted me lo ha confesado mil veces.\n\n\nY as\u00ed se pasaba la vida, haci\u00e9ndola m\u00e1s miserable y menos apetecible de tanto apetecer prolongarla y de tanto temer la muerte.\n\n\n\u00a0\n\n\n* * *\n\n\n\u00a0\n\n\nUn d\u00eda D. Eleuterio se puso muy serio, a la cabecera de la cama de D. Narciso; sac\u00f3 el reloj, tom\u00f3 el pulso, examin\u00f3 detenidamente al enfermo, y con un tono autoritario que, por de pronto, sorprendi\u00f3 y sobrecogi\u00f3 al paciente, impuso su voluntad y declar\u00f3 que iba a recetar una cosa que estaba indicad\u00edsima para evitar complicaciones serias que pod\u00edan sobrevenir, de que ya hab\u00eda indicios. Y no dio m\u00e1s explicaciones; no dijo qu\u00e9 cosa era aquella. Don Narciso asustado, d\u00e9bil, no pudo mostrar la energ\u00eda de otras veces para ponerse al cabo de lo que se iba a hacer con \u00e9l.\n\n\nA sus t\u00edmidas indicaciones, el m\u00e9dico, con voz seca, contest\u00f3 (seguro de ejercer en aquella ocasi\u00f3n cierto poder sugestivo):\n\n\n-No puede usted entender la f\u00f3rmula de esto: es cosa nueva; esta noche he estudiado la cuesti\u00f3n, y resuelvo que esto es lo que conviene; se trata de algo muy complejo, que usted, profano al fin, no comprender\u00eda. Y no hay que andarse con bromas, podr\u00e1 el remedio no servir; pero sin \u00e9l\u2026, es seguro\u2026\n\n\n-\u00bfEl qu\u00e9?\n\n\n-Es seguro que estamos\u2026 mal.\n\n\nCada vez m\u00e1s acoquinado, dijo D. Narciso, por decir algo:\n\n\n-Bueno; pues\u2026 que traigan pluma y papel\u2026 o pase usted al despacho\u2026\n\n\n-No: no hace falta; tengo prisa. Aqu\u00ed mismo; traigo yo papel y l\u00e1piz\u2026 Y esas plumas de usted nunca parecen\u2026 y eso que es usted escritor.\n\n\nY diciendo y haciendo, sac\u00f3 de un bolsillo interior una cartera, busc\u00f3 en ella un papel y un l\u00e1piz, y en pie, apoyando el papel en la cartera misma, escribi\u00f3 r\u00e1pidamente la receta. Quer\u00eda aprovechar aquel momento de dominio sugestivo sobre el enfermo, y no quer\u00eda dilaciones por causa de pormenores materiales. Nervioso, pero con aspecto de triunfo, guard\u00f3 sus chismes de escribir, se despidi\u00f3 con pocas palabras y sali\u00f3, despu\u00e9s de entregar a uno de la familia el papelito, s\u00edmbolo de su victoria sobre el empecatado D. Narciso.\n\n\nVino la medicina, la tom\u00f3 el enfermo, como un doctrino, en la forma que al salir hab\u00eda detallado el m\u00e9dico, y no hubo m\u00e1s.\n\n\n\u00a0\n\n\n* * *\n\n\n\u00a0\n\n\nAs\u00ed, como media hora despu\u00e9s de tragarse la p\u00f3cima, D. Narciso, revolviendo impaciente los pliegues del arrugado embozo del lecho, tropez\u00f3 con un papel escrito.\n\n\n-\u00bfQu\u00e9 es esto? pens\u00f3. \u00bfQui\u00e9n ha dejado esto aqu\u00ed? \u00a1Ah! ya caigo. Este papel se cay\u00f3 de la cartera de D. Eleuterio. -Como no era carta, ni cosa por el estilo, su curiosidad no encontr\u00f3 resistencia cuando le pidi\u00f3 que leyera aquel documento.\n\n\nY ley\u00f3. \u00a1Cosa m\u00e1s rara! Eran unos apuntes que pod\u00edan llamarse reflexiones sueltas acerca de la Medicina en general. \u00a1Pero qu\u00e9 reflexiones (No solo eran incoherentes, sino que subvert\u00edan todo el orden de la terap\u00e9utica, tomaban a contrapelo la patolog\u00eda, y supon\u00edan un criterio de escepticismo caprichoso, respeto de la ciencia tradicional; y en cambio se ve\u00eda clara una tendencia a admitir la eficacia de lo maravilloso, a suponer en la realidad, en el fondo de la qu\u00edmica, seg\u00fan palabras que se le\u00edan all\u00ed, misteriosas relaciones, virtudes cuasi morales de los llamados simples con que no contaba ni pod\u00eda contar la Medicina, porque desconoc\u00eda la naturaleza, y a\u00fan la existencia de tales elementos de la vida natural, y nadie pod\u00eda decir de sus causas ni de sus efectos. Se exageraba en aquel papel la autosugesti\u00f3n; se supon\u00eda que, siendo el hombre microcosmos, ten\u00eda, por autarqu\u00eda y autonom\u00eda de la vida universal-individual, un mundo aparte, individual, de leyes naturales, diferentes para cada cual. As\u00ed como Prot\u00e1goras hab\u00eda dicho que \u00abel hombre era la medida de todo\u00bb con relaci\u00f3n al conocimiento, significando que la verdad para cada cual era diferente, all\u00ed se aseguraba que las enfermedades y los remedios en cada ser individual eran diferentes tambi\u00e9n. Despu\u00e9s ven\u00edan burlas sangrientas, sarcasmos feroces contra m\u00e9dicos, escuelas, hip\u00f3tesis cient\u00edficas, etc., todo en estilo nervios\u00edsimo, entre paradojas e hip\u00e9rboles, incongruencias, im\u00e1genes alambicadas y extravagantes\u2026\n\n\n-No cabe duda, -pens\u00f3 D. Narciso; -este hombre est\u00e1 loco; \u00a1qui\u00e9n lo hab\u00eda de decir! Aqu\u00ed tengo el pensamiento secreto de mi m\u00e9dico: este papel se le ha ca\u00eddo de la cartera cuando la sac\u00f3 para escribir la receta; este papel representa el \u00edntimo pensar de mi m\u00e9dico\u2026 y esto es obra de un loco ilustrado, de un doctor\u2026 a quien se le han hecho los sesos caldo. \u00a1Dios m\u00edo\u2026 y yo estoy en manos de este demente, a merced mi salud de los caprichos de una vesania!\n\n\nY sigui\u00f3 leyendo, y de repente dio un grito espantado. Porque hab\u00eda le\u00eddo esto:\n\n\n\u00abEl \u00fanico m\u00e9dico bueno del mundo no es m\u00e9dico, es m\u00e9dica: la Casualidad\u00bb.\n\n\n\u00abSolo pod\u00e9is curar vuestros males jugando a la loter\u00eda. Una receta debe ser algo as\u00ed como un d\u00e9cimo o muchos d\u00e9cimos. El motivo es obvio. No es cierto que la ignorancia en que estamos del fondo virtual de la esencia de las cosas aconseje la abstenci\u00f3n de medicamentos. El mal, por lo com\u00fan, no desaparece por s\u00ed solo. Lo que hay que hacer es\u2026 jugar a la loter\u00eda el mayor n\u00famero posible de billetes, para aumentar las probabilidades de curar\u2026 y las de reventar. (\u00ab\u00a1Loco rematado!\u00bb gritaba al llegar aqu\u00ed D. Narciso.) El que no se aventura no pasa la mar. El m\u00e9dico y el enfermo deben de ser valientes, jugar el todo por el todo. La receta debe contener la mayor cantidad posible de principios curativos que no se neutralicen, todos de positiva eficacia en su g\u00e9nero. De este modo, si no se ha dado en el clavo, sino en la herradura, se puede matar al paciente, es verdad; pero tambi\u00e9n puede suceder que su mal no tenga relaci\u00f3n ni con el efecto nocivo ni con el ben\u00e9fico del resultado de la combinaci\u00f3n compleja de agentes. Puede tambi\u00e9n suceder que \u00e9sta resulte inofensiva para todo temperamento y para todos los \u00f3rganos, en todos los estados. Y, por \u00faltimo, puede suceder que la acci\u00f3n de alguno de los componentes, o de la reuni\u00f3n de varios, o de la total, sea la que se buscaba a ciegas. Y entonces tenemos la receta modelo\u2026 a posteriori. La firma\u2026 la m\u00e9dica \u00fanica, la Casualidad. Jugad muchos billetes y podr\u00e9is tener m\u00e1s probabilidades de sanar\u2026 o de reventar\u00bb.\n\n\n-\u00a1Reventar, reventar de seguro! -gritaba don Narciso fuera de s\u00ed, casi decidido a saltar de la cama, v\u00edctima del p\u00e1nico.\n\n\nSe colg\u00f3 del cord\u00f3n de la campanilla; ped\u00eda socorro. \u00ab\u00a1Envenenado! \u00a1Estoy envenenado!\u00bb Dec\u00eda lleno de terror a los parientes y criados que rodearon el lecho\u2026\n\n\n-\u00a1Lo que me habr\u00e1 dado ese loco! \u00a1Dios m\u00edo! \u00a1Qu\u00e9 n\u00fameros, qu\u00e9 serie de la loter\u00eda me habr\u00e9 tragado yo!\n\n\n-Pero \u00bfest\u00e1s loco?\u2026 -le preguntaban.\n\n\n-No, yo no; el m\u00e9dico\u2026 Pronto, a escape, un contraveneno\u2026 un vomitivo\u2026\n\n\n-Ir\u00e1n a la botica\u2026\n\n\n-No, no, es tarde; corre prisa\u2026 Aceite, \u00a1todo el aceite que haya en casa!\u2026 \u00a1Venga aceite!\n\n\nBebi\u00f3 no s\u00e9 qu\u00e9 cantidad fabulosa de aceite. Por aquella boca sali\u00f3 a poco\u2026 lo que no puede decirse. Debi\u00f3 de haberse quedado hueco. Le venci\u00f3 la debilidad y se qued\u00f3 entre aletargado y dormido.\n\n\nSe llam\u00f3 a D. Eleuterio. Cuando despert\u00f3 don Narciso lo ten\u00eda inclinado sobre su cabeza, observ\u00e1ndole.\n\n\n-Pero \u00bfqu\u00e9 hace aqu\u00ed ese hombre?\n\n\nDon Eleuterio crey\u00f3 que deliraba. En fin, despu\u00e9s de muchos desprop\u00f3sitos, hubo explicaciones. Don Narciso sinti\u00f3 que se sent\u00eda muy bien.\n\n\n-\u00a1La medicina! -dijo D. Eleuterio.\n\n\n-No, el aceite.\n\n\nEl m\u00e9dico se ech\u00f3 a re\u00edr, y dijo:\n\n\n-Puede.\n\n\nAquel papelito que tanto hab\u00eda alarmado al enfermo no era cosa de su m\u00e9dico; \u00e9ste, por curiosidad lo hab\u00eda recogido entre otros muchos que hab\u00eda dejado un pobre estudiante de Medicina que hab\u00eda muerto loco en el hospital.\n\n\nA los pocos d\u00edas del susto y de desfondarse, don Narciso se paseaba ya por casa y com\u00eda con apetito.\n\n\nY una tarde, D. Eleuterio, que hab\u00eda estudiado muy bien la r\u00e1pida y milagrosa curaci\u00f3n espont\u00e1nea del inaguantable cliente, le dijo:\n\n\n-Pues hay que confesarlo; el loco del hospital\u2026 acert\u00f3 con ese testamento cient\u00edfico. Quien le ha curado a usted ha sido la m\u00e9dica, la Casualidad. Reconozco, s\u00e9 positivamente, que lo que usted necesitaba, y yo no ca\u00eda en ello, no era lo que yo le di, sino lo que usted tom\u00f3 para arrojar lo otro.\n\n\n-\u00bfAceite?\n\n\n-Si no aceite por necesidad, algo que surgiera el mismo efecto. La cosa parece muy grosera; pero la verdad es que usted ten\u00eda dentro algo que no sabemos lo que era; y que le hac\u00eda falta librarse de ello, y se libr\u00f3\u2026 por creer que yo estaba chiflado. Le han curado a usted entre un demente y la Fortuna. Dos locos.\n\n\n-Sobre todo me ha curado,\u2026 la m\u00e9dica.\n\n\n*FIN*\n\n"}